pypushdeer/__init__.py
pypushdeer/pypushdeer.py
pypushdeer-0.0.3.dist-info/LICENSE
pypushdeer-0.0.3.dist-info/METADATA
pypushdeer-0.0.3.dist-info/WHEEL
pypushdeer-0.0.3.dist-info/top_level.txt
pypushdeer-0.0.3.dist-info/RECORD
