Metadata-Version: 2.1
Name: pypushdeer
Version: 0.0.3
Summary: PushDeer for Python
Home-page: https://github.com/gaoliang/pypushdeer
Author: Gao Liang
Author-email: gaoliangim@gmail.com
License: UNKNOWN
Project-URL: Bug Tracker, https://github.com/gaoliang/pypushdeer/issues
Platform: UNKNOWN
Classifier: Programming Language :: Python :: 3
Classifier: Programming Language :: Python :: 3.5
Classifier: Programming Language :: Python :: 3.6
Classifier: Programming Language :: Python :: 3.7
Classifier: Programming Language :: Python :: 3.8
Classifier: Programming Language :: Python :: 3.9
Classifier: Programming Language :: Python :: 3.10
Classifier: License :: OSI Approved :: MIT License
Classifier: Operating System :: OS Independent
Requires-Python: >=3.5
License-File: LICENSE
